dome9/__init__.py
dome9/dome9.py
dome9-0.6.1.dist-info/LICENSE
dome9-0.6.1.dist-info/METADATA
dome9-0.6.1.dist-info/WHEEL
dome9-0.6.1.dist-info/top_level.txt
dome9-0.6.1.dist-info/RECORD
