Metadata-Version: 2.1
Name: dome9
Version: 0.6.1
Summary: Dome9 SDK for Python
Home-page: https://github.com/davidmoremad
Author: David Amrani Hernandez
Author-email: davidmorenomad@gmail.com
License: Apache 2.0
Project-URL: Documentation, https://dome9.readthedocs.io
Project-URL: Source Code, https://github.com/davidmoremad/dome9
Keywords: dome9 sdk cloudsecurity cspm
Platform: UNKNOWN
Classifier: License :: OSI Approved :: Apache Software License
Classifier: Topic :: Software Development :: Libraries :: Python Modules
Classifier: Topic :: Security
Classifier: Environment :: Console
Classifier: Development Status :: 3 - Alpha
Classifier: Intended Audience :: System Administrators
Classifier: Intended Audience :: Information Technology
Classifier: Intended Audience :: Developers
Classifier: Programming Language :: Python
Classifier: Programming Language :: Python :: 2.7
Classifier: Programming Language :: Python :: 3
Classifier: Programming Language :: Python :: 3.6
Classifier: Programming Language :: Python :: 3.7
Classifier: Programming Language :: Python :: 3.8
Classifier: Programming Language :: Python :: 3.9
Classifier: Programming Language :: Python :: 3.10
Classifier: Natural Language :: English
License-File: LICENSE
Requires-Dist: requests
